[{"bbox": [108.0, 68.0, 142.0, 102.0], "color": "red", "material": "rubber"}, {"bbox": [57.0, 25.0, 101.0, 69.0], "color": "red", "material": "metal"}, {"bbox": [75.0, 98.0, 115.0, 138.0], "color": "yellow", "material": "metal"}, {"bbox": [152.0, 120.0, 196.0, 164.0], "color": "blue", "material": "metal"}, {"bbox": [27.0, 137.0, 71.0, 181.0], "color": "purple", "material": "rubber"}, {"bbox": [182.0, 30.0, 216.0, 64.0], "color": "purple", "material": "rubber"}, {"bbox": [141.0, 199.0, 175.0, 233.0], "color": "yellow", "material": "rubber"}, {"bbox": [90.0, 155.0, 130.0, 195.0], "color": "yellow", "material": "metal"}]