{"sentence": ["move the left green block to the rear right side of blocks that you moved before", "move the left green block to the rear right side of the middle yellow and the blue block", "straighten and move the rearmost green block to the rear right of the first moved yellow block", "straighten and move the leftmost green block to the back of the rightmost yellow block", "take the farthest green block from the moved blocks and place it to the rear side of the right yellow block"], "bbox": {"pick": [21, 19, 65, 63], "place": [159, 80, 191, 112]}, "explicit": [true, false, true, false, true], "implicit": [false, true, true, false, false]}