{"sentence": ["move the purple block to the left front center of the blue block you just moved", "move the purple block to the left front corner of the left blue block", "move the purple block so that one corner touches the front left corner of the blue block you just moved", "move the purple block so that one corner touches the front left corner of the left blue block"], "bbox": {"pick": [135, 188, 173, 226], "place": [51, 142, 83, 174]}, "explicit": [true, false, true, false], "implicit": [false, false, false, false]}