{"sentence": ["move the foremost red block to the front right side of the block that you just moved before", "move the front red block to the front right side of the front green block", "move the foremost red block to the front right of the green block that was just moved so that the two blocks touch each other at one corner", "move the foremost red block to the front right of the green block in front of the red block at rear left corner so that the two blocks meet at one corner"], "bbox": {"pick": [137, 192, 177, 232], "place": [68, 99, 100, 131]}, "explicit": [true, false, true, false], "implicit": [false, false, false, false]}