{"sentence": ["move the red block in front of the leftmost red block above the block that you moved just before", "move the red block in front of the leftmost red block above the right green block", "move the front left red block to the top of the last moved green block", "straighten and move the red block on the front left quadrant to the top of the rightmost green block", "pick up the foremost one among the red blocks that you did not move and stack it above the rightmost green block"], "bbox": {"pick": [33, 130, 77, 174], "place": [194, 186, 226, 218]}, "explicit": [true, false, true, false, true], "implicit": [false, false, false, false, false]}