{"sentence": ["move the rear red block to the front of the block that you moved just before", "move the rear red block to the front of the second leftmost blue block", "straighten and move the rearmost red block to the front of the last moved blue block", "pick up the red block next to the moved blocks and place it in front of the block you just moved"], "bbox": {"pick": [59, 78, 97, 116], "place": [142, 99, 174, 131]}, "explicit": [true, false, true, true], "implicit": [false, false, false, false]}