{"sentence": ["move the front red block to the right side of the block that you moved just before", "move the front red block to the right side of the rear yellow block", "straighten and move the front red block behind the yellow block to the right of the last moved yellow block", "straighten and move the foremost red block to the right of the yellow block at rear left corner"], "bbox": {"pick": [176, 144, 220, 188], "place": [70, 38, 102, 70]}, "explicit": [true, false, true, false], "implicit": [false, false, false, false]}